CONTRIBUTORS
LICENSE
MANIFEST.in
README.md
requirements.txt
setup.cfg
setup.py
orcidfind/Dockerfile
orcidfind/__init__.py
orcidfind/__version__.py
orcidfind/find.py
orcidfind.egg-info/PKG-INFO
orcidfind.egg-info/SOURCES.txt
orcidfind.egg-info/dependency_links.txt
orcidfind.egg-info/entry_points.txt
orcidfind.egg-info/requires.txt
orcidfind.egg-info/top_level.txt
orcidsearch/__init__.py
orcidsearch/search.py