Metadata-Version: 1.1
Name: orcidfind
Version: 0.1a.6
Summary: Python script to allow an interactive TTY for searching the Orcid API
Home-page: https://crc.nd.edu
Author: cwilli34
Author-email: cwilli34@nd.edu
License: ALv2
Download-URL: https://github.com/crcresearch/orcidfind/tarball/0.1-alpha.6
Keywords: orcid,python-orcid,pubic,API
Platform: Linux
Classifier: Development Status :: 3 - Alpha
Classifier: Intended Audience :: Developers
Classifier: Intended Audience :: Science/Research
Classifier: License :: OSI Approved :: Apache Software License
Classifier: Natural Language :: English
Classifier: Programming Language :: Python
Classifier: Topic :: Software Development
Classifier: Topic :: Software Development :: Libraries
Classifier: Topic :: Utilities
